<?xml version="1.0" encoding="utf-8"?>
<language>
	<entry name="AstraMilitarum0" value="Ananke"/>
	<entry name="AstraMilitarum1" value="Villae Alea"/>
	<entry name="AstraMilitarum2" value="Legomenon"/>
	<entry name="AstraMilitarum3" value="Ariston"/>
	<entry name="AstraMilitarum4" value="Ourania"/>
	<entry name="AstraMilitarum5" value="Theon"/>
	<entry name="AstraMilitarum6" value="Vicus Phobos"/>
	<entry name="AstraMilitarum7" value="Chrysophorous"/>
	<entry name="AstraMilitarum8" value="Genesin"/>
	<entry name="AstraMilitarum9" value="Heureka"/>
	<entry name="AstraMilitarum10" value="Moenia Creed"/>
	<entry name="AstraMilitarum11" value="Municipium Celestine"/>
	<entry name="AstraMilitarum12" value="Urbs Cawl"/>
	<entry name="AstraMilitarum13" value="Asticus Greyfax"/>
	<entry name="AstraMilitarum14" value="Paradisus Macharius"/>
	<entry name="AstraMilitarum15" value="Oppidum Viridium"/>
	<entry name="AstraMilitarum16" value="Tenax"/>
	<entry name="AstraMilitarum17" value="Civitus Polypus"/>
	<entry name="AstraMilitarumCount" value="18"/>
	<entry name="Necrons0" value="Lecton Kopt"/>
	<entry name="Necrons1" value="The Doom of Abyda"/> 
	<entry name="Necrons2" value="Obol Hermonkh"/>
	<entry name="Necrons3" value="Unkhi Sayr"/>
	<entry name="Necrons4" value="Nekhakh Bakyr"/>
	<entry name="Necrons5" value="Az Ptek Sanakht"/>
	<entry name="Necrons6" value="Iah Khabimh"/>
	<entry name="Necrons7" value="Abdu Khmun"/>
	<entry name="Necrons8" value="Tanis Ta"/>
	<entry name="Necrons9" value="Szar Agorekh"/> 
	<entry name="Necrons10" value="Shabt Mandrekh"/>
	<entry name="Necrons11" value="Tramun Szekh"/>
	<entry name="Necrons12" value="Ftan Heka"/>
	<entry name="Necrons13" value="Echaton Djet"/>
	<entry name="Necrons14" value="Bakenkhon"/>
	<entry name="Necrons15" value="Hierakon Khar"/>
	<entry name="Necrons16" value="D'kan Mephet"/>
	<entry name="Necrons17" value="Gorod'tyr"/>
	<entry name="NecronsCount" value="18"/>
	<entry name="Orks0" value="Da Drops"/>
	<entry name="Orks1" value="Sum Gubbinz"/>
	<entry name="Orks2" value="Grottown"/>
	<entry name="Orks3" value="Dat Rock"/>
	<entry name="Orks4" value="Oo Cares?"/>
	<entry name="Orks5" value="Nazdreg Wos Ere"/>
	<entry name="Orks6" value="Garaghak"/>
	<entry name="Orks7" value="Wazzdakka"/>
	<entry name="Orks8" value="Da Boss's Place"/>
	<entry name="Orks9" value="Da Dakka Klub"/>
	<entry name="Orks10" value="Dat Fing"/>
	<entry name="Orks11" value="'Ome"/>
	<entry name="Orks12" value="Doktown"/>
	<entry name="Orks13" value="Fork Gork"/>
	<entry name="Orks14" value="Gargates"/>
	<entry name="Orks15" value="Rokclaw"/> 
	<entry name="Orks16" value="Da 'Eap"/>
	<entry name="Orks17" value="Da Empire of Da Orks"/>
	<entry name="OrksCount" value="18"/>
	<entry name="SpaceMarines0" value="Fortress of Dorn"/>
	<entry name="SpaceMarines1" value="Primaris Revenant"/>
	<entry name="SpaceMarines2" value="Vulkan's Forge"/>
	<entry name="SpaceMarines3" value="The Spire"/>
	<entry name="SpaceMarines4" value="The Wings of Corax"/>
	<entry name="SpaceMarines5" value="Helbrecht"/>
	<entry name="SpaceMarines6" value="Oubliette of the Faithful"/>
	<entry name="SpaceMarines7" value="The Umbran Citadel"/>
	<entry name="SpaceMarines8" value="Pater Fidelium"/>
	<entry name="SpaceMarines9" value="Azrael's Wrath"/>
	<entry name="SpaceMarines10" value="Tantaline Fall"/>
	<entry name="SpaceMarines11" value="Primarch's Rest"/>
	<entry name="SpaceMarines12" value="Chapel of the Adytum"/>
	<entry name="SpaceMarines13" value="Cor Imperii"/>
	<entry name="SpaceMarines14" value="Arx Mortifer"/>
	<entry name="SpaceMarines15" value="Castellum Capitalis"/>
	<entry name="SpaceMarines16" value="Regia Funestes"/>
	<entry name="SpaceMarines17" value="Stygian Moene"/>
	<entry name="SpaceMarinesCount" value="18"/>
	<entry name="Tyranids0" value="Jejungon"/>
	<entry name="Tyranids1" value="Duodevore"/>
	<entry name="Tyranids2" value="Trachynx"/>
	<entry name="Tyranids3" value="Pharchor"/>
	<entry name="Tyranids4" value="Bronchea"/>
	<entry name="Tyranids5" value="Oesofex"/>
	<entry name="Tyranids6" value="Panuretor"/>
	<entry name="Tyranids7" value="Electrocrine"/>
	<entry name="Tyranids8" value="Hypolymphex"/>
	<entry name="Tyranids9" value="Tervithroid"/>
	<entry name="Tyranids10" value="Somater"/>
	<entry name="Tyranids11" value="Endothelone"/>
	<entry name="Tyranids12" value="Cilior"/>
	<entry name="Tyranids13" value="Tyrannothelium"/>
	<entry name="Tyranids14" value="Dimacheura"/>
	<entry name="Tyranids15" value="Gauphagus"/> 
	<entry name="Tyranids16" value="Gonadrenal"/>
	<entry name="Tyranids17" value="Paralympfex"/>
	<entry name="TyranidsCount" value="18"/>
</language>